odoo8_addon_connector_generic-8.0.0.0.1-py3.8-nspkg.pth
odoo_addons/connector_generic/__init__.py
odoo_addons/connector_generic/__openerp__.py
odoo_addons/connector_generic/consumer.py
odoo_addons/connector_generic/unit/__init__.py
odoo_addons/connector_generic/unit/deleter.py
odoo_addons/connector_generic/unit/exporter.py
odoo_addons/connector_generic/unit/mapper.py
odoo8_addon_connector_generic-8.0.0.0.1.dist-info/METADATA
odoo8_addon_connector_generic-8.0.0.0.1.dist-info/WHEEL
odoo8_addon_connector_generic-8.0.0.0.1.dist-info/namespace_packages.txt
odoo8_addon_connector_generic-8.0.0.0.1.dist-info/top_level.txt
odoo8_addon_connector_generic-8.0.0.0.1.dist-info/RECORD
